libadvian/__init__.py
libadvian/binpackers.py
libadvian/classloader.py
libadvian/hashinghelpers.py
libadvian/iter.py
libadvian/logging/__init__.py
libadvian/logging/common.py
libadvian/logging/httpmulti.py
libadvian/py.typed
libadvian/tasks.py
libadvian/testhelpers.py
libadvian-1.9.0.dist-info/LICENSE
libadvian-1.9.0.dist-info/METADATA
libadvian-1.9.0.dist-info/WHEEL
libadvian-1.9.0.dist-info/RECORD
