Metadata-Version: 2.3
Name: libadvian
Version: 1.9.0
Summary: Small helpers that do not warrant their own library
License: MIT
Author: Eero af Heurlin
Author-email: eero.afheurlin@advian.fi
Requires-Python: >=3.9,<4.0
Classifier: License :: OSI Approved :: MIT License
Classifier: Programming Language :: Python :: 3
Classifier: Programming Language :: Python :: 3.9
Classifier: Programming Language :: Python :: 3.10
Classifier: Programming Language :: Python :: 3.11
Classifier: Programming Language :: Python :: 3.12
Classifier: Programming Language :: Python :: 3.13
Provides-Extra: all
Provides-Extra: http
Provides-Extra: logstash
Provides-Extra: vector
Requires-Dist: frozendict ; extra == "http"
Requires-Dist: http ; extra == "all"
Requires-Dist: http ; extra == "logstash"
Requires-Dist: http ; extra == "vector"
Requires-Dist: requests ; extra == "http"
